qldpc/__init__.py
qldpc/abstract.py
qldpc/abstract_test.py
qldpc/cache.py
qldpc/cache_test.py
qldpc/circuits/__init__.py
qldpc/circuits/bookkeeping.py
qldpc/circuits/bookkeeping_test.py
qldpc/circuits/common.py
qldpc/circuits/common_test.py
qldpc/circuits/memory.py
qldpc/circuits/memory_test.py
qldpc/circuits/noise_model.py
qldpc/circuits/noise_model_test.py
qldpc/circuits/syndrome_measurement.py
qldpc/circuits/syndrome_measurement_test.py
qldpc/circuits/transversal.py
qldpc/circuits/transversal_test.py
qldpc/codes/__init__.py
qldpc/codes/classical.py
qldpc/codes/classical_test.py
qldpc/codes/common.py
qldpc/codes/common_test.py
qldpc/codes/distance.py
qldpc/codes/distance_test.py
qldpc/codes/quantum.py
qldpc/codes/quantum_test.py
qldpc/decoders/__init__.py
qldpc/decoders/custom.py
qldpc/decoders/custom_test.py
qldpc/decoders/dems.py
qldpc/decoders/dems_test.py
qldpc/decoders/retrieval.py
qldpc/decoders/retrieval_test.py
qldpc/decoders/sinter.py
qldpc/decoders/sinter_test.py
qldpc/external/__init__.py
qldpc/external/codes.py
qldpc/external/codes_test.py
qldpc/external/gap.py
qldpc/external/gap_test.py
qldpc/external/groups.py
qldpc/external/groups_test.py
qldpc/math.py
qldpc/math_test.py
qldpc/objects.py
qldpc/objects_test.py
qldpc/py.typed
qldpc-0.2.7.dist-info/WHEEL
qldpc-0.2.7.dist-info/METADATA
qldpc-0.2.7.dist-info/RECORD
