Metadata-Version: 2.4
Name: qLDPC
Version: 0.2.7
Summary: Tools for constructing and analyzing quantum low density parity check (qLDPC) codes.
Keywords: quantum computing,quantum error correction,low density parity check codes,LDPC
Author: Michael A. Perlin
Author-email: Michael A. Perlin <mika.perlin@gmail.com>
License-Expression: Apache-2.0
Classifier: Development Status :: 3 - Alpha
Classifier: Intended Audience :: Science/Research
Classifier: Natural Language :: English
Classifier: Topic :: Scientific/Engineering :: Mathematics
Classifier: Topic :: Scientific/Engineering :: Physics
Requires-Dist: cvxpy>=1.3.2
Requires-Dist: diskcache>=5.0.0
Requires-Dist: galois>=0.4.2
Requires-Dist: ldpc>=2.4.1
Requires-Dist: networkx>=2.6.2
Requires-Dist: numpy>=1.24.0
Requires-Dist: platformdirs>=4.0.0
Requires-Dist: pymatching>=2.1.0
Requires-Dist: pyperclip>=1.11.0
Requires-Dist: scipy>=1.14.1
Requires-Dist: stim>=1.16.dev1768963940
Requires-Dist: sympy>=1.12
Requires-Dist: checks-superstaq>=0.5.45 ; extra == 'dev'
Requires-Dist: jupyter>=1.1.1 ; extra == 'dev'
Requires-Dist: python-lsp-server[all]>=1.14.0 ; extra == 'dev'
Requires-Dist: relay-bp[stim]==0.1.0 ; extra == 'dev'
Requires-Dist: relay-bp[stim]==0.1.0 ; extra == 'relay-bp'
Requires-Python: >=3.10
Project-URL: Repository, https://github.com/qLDPCOrg/qLDPC
Provides-Extra: dev
Provides-Extra: relay-bp
